main.py
pickaxe_mcp_file_system-0.1.2.dist-info/METADATA
pickaxe_mcp_file_system-0.1.2.dist-info/WHEEL
pickaxe_mcp_file_system-0.1.2.dist-info/entry_points.txt
pickaxe_mcp_file_system-0.1.2.dist-info/top_level.txt
pickaxe_mcp_file_system-0.1.2.dist-info/RECORD
