Metadata-Version: 2.4
Name: pickaxe-mcp-file-system
Version: 0.1.2
Summary: A simple file system MCP server.
Requires-Python: >=3.12
Requires-Dist: httpx>=0.28.1
Requires-Dist: mcp[cli]>=1.9.4
Requires-Dist: fastmcp>=2.7.0
